Pyhoot/Client.py
Pyhoot/Exceptions.py
Pyhoot/Token.py
Pyhoot/__init__.py
Pyhoot-1.4.2.dist-info/METADATA
Pyhoot-1.4.2.dist-info/WHEEL
Pyhoot-1.4.2.dist-info/top_level.txt
Pyhoot-1.4.2.dist-info/RECORD
