Metadata-Version: 2.1
Name: Pyhoot
Version: 1.4.2
Summary: A Python library used for the Kahoot! Api
Author: Maxgamertyper1 (Max Allen)
Author-email: maxa5302@gmail.com
License: MIT
Keywords: Python,Kahoot,Pyhoot,bot,flooder,Kahoot!,Library,Api,Kahoot api,Kahoot Python
Classifier: Development Status :: 5 - Production/Stable
Classifier: Intended Audience :: Developers
Classifier: Programming Language :: Python :: 3
Classifier: Operating System :: Unix
Classifier: Operating System :: MacOS :: MacOS X
Classifier: Operating System :: Microsoft :: Windows
Requires-Python: >=3.6
Requires-Dist: requests
Requires-Dist: beautifulsoup4
Requires-Dist: websocket-client
Requires-Dist: fake-useragent
